Workbook

Sheet Resumo
A1: Relatório de Qualidade UI/UX — PatientPal / ClinicaOS
A2: Análise de interatividade, inconsistências, duplicidade e layout · 09/07/2026
A4: Totais
A5: Total de apontamentos | B5: =COUNTA('Relatório de Erros'!A2:A39) -> 38
A6: Corrigidos nesta análise | B6: =COUNTIF('Relatório de Erros'!I2:I39,"Corrigido") -> 5
A7: Pendentes | B7: =COUNTIF('Relatório de Erros'!I2:I39,"Pendente") -> 33
A9: Por categoria e severidade
A10: Categoria | B10: Alta | C10: Média | D10: Baixa | E10: Total
A11: Interatividade | B11: =COUNTIFS('Relatório de Erros'!B2:B39,"Interatividade",'Relatório de Erros'!C2:C39,"Alta") -> 2 | C11: =COUNTIFS('Relatório de Erros'!B2:B39,"Interatividade",'Relatório de Erros'!C2:C39,"Média") -> 4 | D11: =COUNTIFS('Relatório de Erros'!B2:B39,"Interatividade",'Relatório de Erros'!C2:C39,"Baixa") -> 1 | E11: =SUM(B11:D11) -> 7
A12: Duplicidade | B12: =COUNTIFS('Relatório de Erros'!B2:B39,"Duplicidade",'Relatório de Erros'!C2:C39,"Alta") -> 2 | C12: =COUNTIFS('Relatório de Erros'!B2:B39,"Duplicidade",'Relatório de Erros'!C2:C39,"Média") -> 3 | D12: =COUNTIFS('Relatório de Erros'!B2:B39,"Duplicidade",'Relatório de Erros'!C2:C39,"Baixa") -> 1 | E12: =SUM(B12:D12) -> 6
A13: Inconsistência | B13: =COUNTIFS('Relatório de Erros'!B2:B39,"Inconsistência",'Relatório de Erros'!C2:C39,"Alta") -> 1 | C13: =COUNTIFS('Relatório de Erros'!B2:B39,"Inconsistência",'Relatório de Erros'!C2:C39,"Média") -> 3 | D13: =COUNTIFS('Relatório de Erros'!B2:B39,"Inconsistência",'Relatório de Erros'!C2:C39,"Baixa") -> 2 | E13: =SUM(B13:D13) -> 6
A14: Layout | B14: =COUNTIFS('Relatório de Erros'!B2:B39,"Layout",'Relatório de Erros'!C2:C39,"Alta") -> 3 | C14: =COUNTIFS('Relatório de Erros'!B2:B39,"Layout",'Relatório de Erros'!C2:C39,"Média") -> 4 | D14: =COUNTIFS('Relatório de Erros'!B2:B39,"Layout",'Relatório de Erros'!C2:C39,"Baixa") -> 1 | E14: =SUM(B14:D14) -> 8
A15: Sintaxe | B15: =COUNTIFS('Relatório de Erros'!B2:B39,"Sintaxe",'Relatório de Erros'!C2:C39,"Alta") -> 1 | C15: =COUNTIFS('Relatório de Erros'!B2:B39,"Sintaxe",'Relatório de Erros'!C2:C39,"Média") -> 1 | D15: =COUNTIFS('Relatório de Erros'!B2:B39,"Sintaxe",'Relatório de Erros'!C2:C39,"Baixa") -> 0 | E15: =SUM(B15:D15) -> 2
A16: Segurança | B16: =COUNTIFS('Relatório de Erros'!B2:B39,"Segurança",'Relatório de Erros'!C2:C39,"Alta") -> 2 | C16: =COUNTIFS('Relatório de Erros'!B2:B39,"Segurança",'Relatório de Erros'!C2:C39,"Média") -> 2 | D16: =COUNTIFS('Relatório de Erros'!B2:B39,"Segurança",'Relatório de Erros'!C2:C39,"Baixa") -> 1 | E16: =SUM(B16:D16) -> 5
A17: Regras de Negócio | B17: =COUNTIFS('Relatório de Erros'!B2:B39,"Regras de Negócio",'Relatório de Erros'!C2:C39,"Alta") -> 1 | C17: =COUNTIFS('Relatório de Erros'!B2:B39,"Regras de Negócio",'Relatório de Erros'!C2:C39,"Média") -> 3 | D17: =COUNTIFS('Relatório de Erros'!B2:B39,"Regras de Negócio",'Relatório de Erros'!C2:C39,"Baixa") -> 0 | E17: =SUM(B17:D17) -> 4
A18: Total | B18: =SUM(B11:B17) -> 12 | C18: =SUM(C11:C17) -> 20 | D18: =SUM(D11:D17) -> 6 | E18: =SUM(E11:E17) -> 38
A20: Leitura recomendada
A21: 1. Aba “Relatório de Erros”: lista completa com severidade, evidência (arquivo:linha), impacto e recomendação. Use os filtros do cabeçalho.
A22: 2. Aba “Módulos do Sistema”: mapa funcional do sistema e a situação de cada módulo (estável, duplicado v1/v2, dev).
A23: 3. Itens “Corrigido” já foram resolvidos no código nesta sessão (responsividade e espaçamentos).
A24: 4. Prioridade sugerida (severidade Alta): 1º segurança — permissão só no menu e segredos expostos no cliente; 2º o confirm() de cancelamento de pacote (cancela agendamento de quem quer desistir); 3º modais/navegação; 4º duplicidade v1/v2.

Sheet Relatório de Erros
A1: ID | B1: Categoria | C1: Severidade | D1: Tela / Área | E1: Arquivo (evidência) | F1: Problema | G1: Impacto para o usuário | H1: Recomendação | I1: Status
A2: 1 | B2: Interatividade | C2: Alta | D2: Todos os modais do sistema | E2: src/components/ui/dialog.tsx:44-46 | F2: Modais não fecham com ESC nem clicando fora (preventDefault aplicado globalmente no DialogContent) | G2: Usuário fica “preso” no modal e só sai pelo X ou pelo botão Cancelar; foge do padrão esperado | H2: Remover os preventDefault globais; bloquear fechamento apenas em modais com formulário preenchido | I2: Pendente
A3: 2 | B3: Interatividade | C3: Alta | D3: Menu lateral (todas as telas) | E3: src/components/app-shell.tsx:618, 649 | F3: Cada clique no menu usa window.location.assign — recarrega a aplicação inteira em vez de navegar via SPA | G3: Navegação lenta (recarrega tudo do zero) e perda de estado de filtros e telas abertas | H3: Trocar por Link/navigate do TanStack Router | I3: Pendente
A4: 3 | B4: Interatividade | C4: Média | D4: Caixa, Nina e Agenda | E4: caixa-shell.tsx:391,400; AtendimentoExtraTabs.tsx:394; app.agenda.tsx:4898 | F4: Mais 4 pontos com recarga completa de página via window.location | G4: Mesmo impacto: lentidão e perda de contexto ao navegar | H4: Trocar por navegação do router | I4: Pendente
A5: 4 | B5: Interatividade | C5: Média | D5: 20+ telas (exclusões e ações em massa) | E5: regras-tab.tsx, planos-page.tsx, contratos-page.tsx, app.agenda.tsx, AtendimentoTabs.tsx… | F5: Uso de confirm()/alert() nativos do navegador em ~20 pontos, enquanto outras telas usam AlertDialog estilizado | G5: Caixas de diálogo cruas, sem identidade visual, que travam a página; experiência desigual entre telas | H5: Padronizar todas as confirmações com o AlertDialog do design system | I5: Pendente
A6: 5 | B6: Interatividade | C6: Média | D6: Diversos módulos | E6: 11 blocos “catch {}” vazios em src/ | F6: Erros engolidos em silêncio, sem toast nem log | G6: Ação pode falhar e o usuário acredita que salvou; suporte fica sem rastro do erro | H6: Exibir toast de erro e registrar o erro em todos os catch | I6: Pendente
A7: 6 | B7: Interatividade | C7: Média | D7: Fluxo, Caixa, Agenda (botões compactos) | E7: 88 ocorrências de h-6 (24px); 224 de text-[10px] | F7: Botões de 24px de altura e fontes de 10px — abaixo do mínimo recomendado de toque (40px+) e de leitura | G7: Difícil acertar o clique em tablets/touch (recepção usa touch); legibilidade ruim | H7: Elevar mínimo para h-8 e text-xs nos controles interativos | I7: Pendente
A8: 7 | B8: Interatividade | C8: Baixa | D8: Cartão Benefícios — recorte de imagem | E8: image-crop-dialog.tsx:181 | F8: Erro de CORS exibido com alert() nativo | G8: Mensagem técnica e fora do padrão visual | H8: Exibir a falha como toast ou mensagem inline no dialog | I8: Pendente
A9: 8 | B9: Duplicidade | C9: Alta | D9: Agenda | E9: app.agenda.tsx (5.338 linhas) + agenda-v2/* (flag agenda_v2) | F9: Duas agendas completas coexistem atrás de feature flag — inclusive lógica de cancelamento de pacote copiada e colada nas duas (agenda-v2-shell.tsx:668 e app.agenda.tsx:2809) | G9: Correções feitas numa agenda não valem na outra; usuários diferentes veem comportamentos diferentes | H9: Concluir a migração para a v2 e remover a versão antiga | I9: Pendente
A10: 9 | B10: Duplicidade | C10: Alta | D10: Caixa, Orçamentos e Menu | E10: app.caixa + caixa-v2; app.orcamentos + orcamentos-v2; app-shell + menu-v2 | F10: Mais 3 módulos inteiros duplicados em versões v1/v2 sob feature flags (menu v2 só para admin/gestor) | G10: Manutenção dobrada e experiência inconsistente entre perfis de usuário | H10: Definir prazo de migração e eliminar as versões antigas | I10: Pendente
A11: 10 | B11: Duplicidade | C11: Média | D11: Barras de KPI | E11: agenda-v2/kpi-bar.tsx, caixa-v2/kpi-bar.tsx, clientes-v2/kpi-bar.tsx, orcamentos-v2/kpi-bar.tsx | F11: 4 implementações diferentes de barra de KPI, duas exportando o mesmo nome “KpiBar” | G11: Visual e interação divergentes entre telas equivalentes; risco de import trocado | H11: Unificar sobre o design system (HhpKpiRow/HhpKpiCard já existem) | I11: Pendente
A12: 11 | B12: Duplicidade | C12: Média | D12: Cadastro de pessoas | E12: /app/equipe, /app/funcionarios, /app/medicos | F12: 3 telas distintas e sobrepostas para gestão de pessoas | G12: Usuário não sabe onde cadastrar; risco de dados divergentes | H12: Consolidar tudo na tela Equipe e redirecionar as demais | I12: Pendente
A13: 12 | B13: Duplicidade | C13: Média | D13: Sistema (produção) | E13: 6 rotas /app/dev-* (dev-hhp, dev-caixa-shell, dev-list-shell…) | F13: Telas de desenvolvimento/showcase empacotadas no build de produção, protegidas apenas por checagem de role no cliente | G13: Peso extra no bundle e telas de teste acessíveis por URL | H13: Excluir do build de produção (guard com import.meta.env.DEV) | I13: Pendente
... A39: 38 | B39: Regras de Negócio | C39: Média | D39: Permissões — regra padrão ambígua | E39: app-shell.tsx:126-131 (leafAllowed / ROUTE_TO_MODULE) | F39: Rota não mapeada em ROUTE_TO_MODULE some do menu por padrão, mas continua acessível por URL; o menu v2 tem catálogo próprio e pode divergir | G39: Telas novas “desaparecem” do menu sem explicação e a regra de acesso fica ambígua entre menu, URL e banco | H39: Fonte única de verdade módulo×rota compartilhada pelo menu (v1 e v2) e pelo guard de rota | I39: Pendente

Sheet Módulos do Sistema
A1: Módulo | B1: Rota principal | C1: Função | D1: Situação | E1: Observação
A2: Agenda | B2: /app/agenda | C2: Agendamento de consultas e horários médicos | D2: Duplicado (v1 + v2 por flag) | E2: v1 com 5.338 linhas em um único arquivo; v2 atrás da flag agenda_v2
A3: Agenda Express | B3: /app/agenda/express | C3: Agendamento rápido simplificado | D3: Estável
A4: Check-in | B4: /app/checkin | C4: Chegada do paciente na recepção | D4: Estável
A5: Caixa | B5: /app/caixa | C5: Recebimentos e fechamento de caixa | D5: Duplicado (v1 + v2 por flag) | E5: Botões da v2 recarregam a página ao voltar para a v1
A6: Fluxo do paciente | B6: /app/fluxo | C6: Kanban das etapas do atendimento | D6: Estável | E6: Kanban de 7 colunas corrigido para escala responsiva
A7: Clientes / Pacientes | B7: /app/clientes | C7: Cadastro e gestão de pacientes | D7: Duplicado (shell v2 em dev) | E7: Edição de paciente espalhada em 4 componentes diferentes
A8: Orçamentos | B8: /app/orcamentos | C8: Criação e conversão de orçamentos | D8: Duplicado (v1 + v2 por flag)
A9: Recepção / Filas | B9: /app/recepcao | C9: Gestão de filas de espera | D9: Estável
A10: Triagem Enfermagem | B10: /app/triagem-enfermagem | C10: Triagem e sinais vitais | D10: Estável
A11: Cartão Benefícios | B11: /app/cartao-beneficios/* | C11: Planos, contratos, convênios e dependentes | D11: Estável | E11: Vários confirm() nativos; tabela de regras de 1400px (tem scroll)
A12: Atendimento médico (IA) | B12: /app/atendimento-ia | C12: Prontuário assistido por IA | D12: Estável
A13: Nina — WhatsApp | B13: /app/nina | C13: Atendimento automatizado e inbox WhatsApp | D13: Estável | E13: 14 sub-telas numa única rota via hash; colunas fixas sem versão mobile
A14: CRM / Marketing | B14: /app/crm, /app/mkt-* | C14: Leads, campanhas, envios e landing pages | D14: Estável
A15: Financeiro | B15: /app/financeiro/* | C15: Contas, movimento, notas, BI e repasse médico | D15: Estável | E15: 14 sub-rotas; maior módulo do sistema
A16: Equipe | B16: /app/equipe | C16: Gestão de médicos, enfermeiros e funcionários | D16: Sobreposto | E16: Concorre com /app/funcionarios e /app/medicos
A17: RH | B17: /app/hr-* | C17: Ponto, contratos, férias e holerites | D17: Estável
A18: Relatórios / BI | B18: /app/relatorios, /app/painel-executivo | C18: Dashboards e cubo BI | D18: Estável
A19: Segurança & Compliance | B19: /app/auditoria, /app/lgpd, /app/perfis | C19: Auditoria, LGPD e perfis de acesso | D19: Estável
A20: Portal do Paciente | B20: /paciente/*, /p/$token | C20: Área pública do paciente (mobile-first) | D20: Estável | E20: Grids corrigidos para mobile nesta análise
A21: Totem / Autoatendimento | B21: /totem, /autoatendimento | C21: Check-in em quiosque | D21: Estável | E21: Larguras fixas aceitáveis (uso em quiosque)
A22: Menu / Shell | B22: (todas as telas) | C22: Navegação, permissões e troca de clínica | D22: Duplicado (v1 + v2 por flag) | E22: Menu v2 só admin/gestor; links do v1 recarregam a página
A23: Telas dev-* | B23: /app/dev-* | C23: Showcases internos de desenvolvimento | D23: Não deveria ir a produção | E23: 6 rotas no bundle de produção
